_icepyx_version.py
icepyx/__init__.py
icepyx/conftest.py
icepyx/core/APIformatting.py
icepyx/core/__init__.py
icepyx/core/auth.py
icepyx/core/exceptions.py
icepyx/core/granules.py
icepyx/core/harmony.py
icepyx/core/is2ref.py
icepyx/core/orders.py
icepyx/core/query.py
icepyx/core/read.py
icepyx/core/spatial.py
icepyx/core/temporal.py
icepyx/core/types.py
icepyx/core/urls.py
icepyx/core/validate_inputs.py
icepyx/core/variables.py
icepyx/core/visualization.py
icepyx/quest/__init__.py
icepyx/quest/quest.py
icepyx/quest/dataset_scripts/__init__.py
icepyx/quest/dataset_scripts/argo.py
icepyx/quest/dataset_scripts/dataset.py
icepyx-2.0.0.dist-info/licenses/LICENSE
icepyx-2.0.0.dist-info/METADATA
icepyx-2.0.0.dist-info/WHEEL
icepyx-2.0.0.dist-info/top_level.txt
icepyx-2.0.0.dist-info/RECORD
