Metadata-Version: 2.4
Name: icepyx
Version: 2.0.0
Summary: Python tools for obtaining and working with ICESat-2 data
Author-email: The icepyx Developers <jbscheick@gmail.com>
Maintainer-email: The icepyx Developers <jbscheick@gmail.com>
License: BSD 3-Clause License
Project-URL: Homepage, https://icepyx.readthedocs.io
Project-URL: Documentation, https://icepyx.readthedocs.io
Project-URL: Repository, https://github.com/icesat2py/icepyx
Project-URL: Issues, https://github.com/icesat2py/icepyx/issues
Project-URL: Changelog, https://icepyx.readthedocs.io/en/latest/user_guide/changelog/index.html
Classifier: Development Status :: 4 - Beta
Classifier: Intended Audience :: Science/Research
Classifier: License :: OSI Approved :: BSD License
Classifier: Operating System :: OS Independent
Classifier: Programming Language :: Python :: 3
Classifier: Programming Language :: Python :: 3.11
Classifier: Programming Language :: Python :: 3.12
Classifier: Programming Language :: Python :: 3.13
Classifier: Topic :: Scientific/Engineering
Classifier: Topic :: Scientific/Engineering :: GIS
Classifier: Topic :: Software Development :: Libraries
Requires-Python: >=3.11
License-File: LICENSE
Requires-Dist: backoff
Requires-Dist: dask[dataframe]<2025.1.0
Requires-Dist: datashader
Requires-Dist: deprecated
Requires-Dist: earthaccess>=0.12.0
Requires-Dist: fiona
Requires-Dist: geopandas
Requires-Dist: h5netcdf
Requires-Dist: h5py
Requires-Dist: harmony-py>=1.0.0
Requires-Dist: holoviews
Requires-Dist: hvplot
Requires-Dist: matplotlib
Requires-Dist: numpy
Requires-Dist: requests
Requires-Dist: s3fs
Requires-Dist: shapely
Requires-Dist: xarray
Provides-Extra: viz
Requires-Dist: geoviews>=1.9.0; extra == "viz"
Requires-Dist: cartopy>=0.18.0; extra == "viz"
Requires-Dist: scipy; extra == "viz"
Provides-Extra: complete
Requires-Dist: icepyx[viz]; extra == "complete"
Dynamic: license-file
